syn.v
//多比特移位寄存器，打两拍，利用两级采样法使时钟同步
module syn(
input wire rst_n,
input wire syn_clk,
input wire [WIDTH - 1:0] syn_data_in,
output wire [WIDTH - 1:0] syn_data_out
);

parameter WIDTH = 5;

reg [WIDTH - 1:0] reg_0;
reg [WIDTH - 1:0] reg_1;
assign syn_data_out = reg_1;

always @(posedge syn_clk or negedge rst_n)begin
    if(!rst_n)begin
        reg_0 <= 0;
        reg_1 <= 0;
    end else begin
        reg_0 <= syn_data_in;
        reg_1 <= reg_0;
    end
end

endmodule

ram.v
module ram(
input wire w_clk,
input wire r_clk,
input wire en_write,
input wire en_read,
input wire [ADDR_WIDTH - 1:0] w_addr,
input wire [ADDR_WIDTH - 1:0] r_addr,
input wire [RAM_WIDTH - 1:0] w_data,
output reg [RAM_WIDTH - 1:0] r_data
);

reg [RAM_WIDTH - 1:0] memory[RAM_HIGH - 1:0];

parameter ADDR_WIDTH = 4;
parameter RAM_HIGH = 16;
parameter RAM_WIDTH = 8;

always @(posedge r_clk)begin
    if(en_read)begin
        r_data <= memory[r_addr];
    end
end

always @(posedge w_clk)begin
    if(en_write)begin
        memory[w_addr] <= w_data;
    end
end 

endmodule

bin_to_gray.v
//二进制转格雷码，第一位不变，其余为当前以及前一位的异或
module bin_to_gray (
input wire [WIDTH - 1:0] bin,
output wire [WIDTH - 1:0] gray
);

wire high_bit_bin = bin[WIDTH - 1] ;
reg [WIDTH - 2:0] low_bit_gray;
integer i;
parameter WIDTH = 5; //包含地址溢出位

always @(*)begin
    for(i = 0;i < WIDTH - 1;i++)begin
        low_bit_gray[i] = bin[i+1]^bin[i];
    end
end

assign gray = {high_bit_bin,low_bit_gray};
    
endmodule

read_control.v
//`include "bin_to_gray.v" //将二进制转格雷码放在写控制模块内

module read_control (
input wire r_clk,
input wire r_rst,
input wire r_req,
input wire [ADDR_WIDTH: 0] w_g_syn_addr, //使用有扩展位地址
output wire [ADDR_WIDTH: 0] r_g_addr,
output reg [ADDR_WIDTH: 0] r_addr,
output wire r_empty
);

parameter ADDR_WIDTH = 4;

bin_to_gray write_comtrol(
    .bin(r_addr),
    .gray(r_g_addr)
);

always @(posedge r_clk or negedge r_rst) begin
    if(!r_rst)begin
        r_addr <= 0;
    end else if(r_req && !(r_empty))begin
        r_addr <= r_addr + 'b1;
    end
end

assign r_empty = (w_g_syn_addr == r_g_addr)? 1:0;

endmodule

write_control.v
//`include "bin_to_gray.v" //将二进制转格雷码放在写控制模块内

module write_control (
input wire w_clk,
input wire w_rst,
input wire w_req,
input wire [ADDR_WIDTH: 0] r_g_syn_addr, //使用有扩展位地址
output wire [ADDR_WIDTH: 0] w_g_addr,
output reg [ADDR_WIDTH: 0] w_addr,
output wire w_full
);

parameter ADDR_WIDTH = 4;

bin_to_gray write_control(
    .bin(w_addr),
    .gray(w_g_addr)
);

always @(posedge w_clk or negedge w_rst) begin
    if(!w_rst)begin
        w_addr <= 0;
    end else if(w_req && !(w_full))begin
        w_addr <= w_addr + 'b1;
    end
end

assign w_full = (r_g_syn_addr == {~w_g_addr[ADDR_WIDTH],~w_g_addr[ADDR_WIDTH - 1],w_g_addr[ADDR_WIDTH - 2:0]})? 1:0; //此时是格雷码的比较，不是1****-0****

endmodule

async_fifo.v

module asyn_fifo (
input wire w_clk,
input wire r_clk,
input wire w_rst,
input wire r_rst,
input wire rst_n,
input wire w_req,
input wire r_req,
input wire [RAM_WIDTH - 1:0] w_data,
output wire [RAM_WIDTH - 1:0] r_data,
output wire w_full,
output wire r_empty
);

wire [ADDR_WIDTH: 0] w_addr;
wire [ADDR_WIDTH: 0] r_addr;
wire [ADDR_WIDTH: 0] w_g_addr;
wire [ADDR_WIDTH: 0] r_g_addr;
wire [ADDR_WIDTH: 0] w_g_syn_addr;
wire [ADDR_WIDTH: 0] r_g_syn_addr;
wire en_write;
wire en_read;

assign en_write = (w_req && (!w_full))? 1:0;
assign en_read = (r_req && (!r_empty))? 1:0;

parameter RAM_WIDTH = 8;
parameter ADDR_WIDTH = 4;

write_control asyn_fifo_write_control(
    .w_clk(w_clk),
    .w_rst(w_rst),
    .w_req(w_req),
    .r_g_syn_addr(r_g_syn_addr),
    .w_g_addr(w_g_addr),
    .w_addr(w_addr),
    .w_full(w_full)
);

read_control asyn_fifo_read_control(
    .r_clk(r_clk),
    .r_rst(r_rst),
    .r_req(r_req),
    .r_g_addr(r_g_addr),
    .w_g_syn_addr(w_g_syn_addr),
    .r_addr(r_addr),
    .r_empty(r_empty)
);

ram asyn_fifo_ram(
    .w_clk(w_clk),
    .r_clk(r_clk),
    .en_write(en_write),
    .en_read(en_read),
    .w_addr(w_addr[ADDR_WIDTH - 1:0]),
    .r_addr(r_addr[ADDR_WIDTH - 1:0]),
    .w_data(w_data),
    .r_data(r_data)
);

syn asyn_fifo_syn_w(
    .rst_n(rst_n),
    .syn_clk(w_clk),
    .syn_data_in(r_g_addr),
    .syn_data_out(r_g_syn_addr)
);

syn asyn_fifo_syn_r(
    .rst_n(rst_n),
    .syn_clk(r_clk),
    .syn_data_in(w_g_addr),
    .syn_data_out(w_g_syn_addr)
);
//ram #(
//    .ADDR_WIDTH(ADDR_WIDTH), 可以将参数在例化时传递
//    ...
//    )
//u_ram(
//  .w_clk(w_clk),
//  ...
//);


endmodule

test_top.v
`include "ram.v"
`include "syn.v"
`include "bin_to_gray.v"
`include "write_control.v"
`include "read_control.v"
`include "async_fifo.v"
`timescale 10ns/1ns
module test_top;
reg w_clk;
reg r_clk;
reg w_rst;
reg r_rst;
reg rst_n;
reg w_req;
reg r_req;
reg [RAM_WIDTH - 1:0] w_data;
wire [RAM_WIDTH - 1:0] r_data;
wire w_full;
wire r_empty;

parameter RAM_WIDTH = 8;
parameter TIME_W = 10;
parameter TIME_R = 8;
integer i;

asyn_fifo test_top(
    .w_clk(w_clk),
    .r_clk(r_clk),
    .w_rst(w_rst),
    .r_rst(r_rst),
    .rst_n(rst_n),
    .w_req(w_req),
    .r_req(r_req),
    .w_data(w_data),
    .r_data(r_data),
    .w_full(w_full),
    .r_empty(r_empty)
);

always #(TIME_W/2) begin
    w_clk = ~w_clk;
end

always #(TIME_R/2) begin
    r_clk = ~r_clk;
end

initial begin
    #0 begin
        w_clk = 0;
        r_clk = 0;
        w_rst = 1;
        r_rst = 1;
        rst_n = 1;
        w_req = 0;
        r_req = 0;
        w_data = 0;
    end 
    #2 begin
        w_rst = 0;
        r_rst = 0;
        rst_n = 0;
        w_req = 0;
        r_req = 0;
        w_data = 0;
    end
    #5 begin
        w_rst = 1;
        r_rst = 1;
        rst_n = 1;
        w_req = 0;
        r_req = 0;
        w_data = 0;
    end
    #5 begin
        for(i = 0;i < 18;i++)begin
            #(TIME_W)
            w_req = 1;
            r_req = 0;
            w_data = i;
        end
        for(i = 0;i < 18;i++)begin
            #(TIME_R)
            w_req = 0;
            r_req = 1;
            $display("%d",r_data);
        end
    end
    #5 begin
        w_rst = 1;
        r_rst = 1;
        rst_n = 1;
        w_req = 0;
        r_req = 0;
        w_data = 0;
    end

    #30 $finish;
end

initial begin
    $dumpfile("wave_top.vcd");
    $dumpvars(0,test_top);
end

endmodule

wave_top.vcd
$date
	Thu Jul 21 17:18:53 2022
$end
$version
	Icarus Verilog
$end
$timescale
	1ns
$end
$scope module test_top $end
$scope module test_top $end
$var wire 1 ! r_clk $end
$var wire 1 " r_req $end
$var wire 1 # r_rst $end
$var wire 1 $ rst_n $end
$var wire 1 % w_clk $end
$var wire 8 & w_data [7:0] $end
$var wire 1 ' w_req $end
$var wire 1 ( w_rst $end
$var wire 5 ) w_g_syn_addr [4:0] $end
$var wire 5 * w_g_addr [4:0] $end
$var wire 1 + w_full $end
$var wire 5 , w_addr [4:0] $end
$var wire 5 - r_g_syn_addr [4:0] $end
$var wire 5 . r_g_addr [4:0] $end
$var wire 1 / r_empty $end
$var wire 8 0 r_data [7:0] $end
$var wire 5 1 r_addr [4:0] $end
$var wire 1 2 en_write $end
$var wire 1 3 en_read $end
$scope module asyn_fifo_ram $end
$var wire 1 3 en_read $end
$var wire 1 2 en_write $end
$var wire 4 4 r_addr [3:0] $end
$var wire 1 ! r_clk $end
$var wire 4 5 w_addr [3:0] $end
$var wire 1 % w_clk $end
$var wire 8 6 w_data [7:0] $end
$var reg 8 7 r_data [7:0] $end
$upscope $end
$scope module asyn_fifo_read_control $end
$var wire 1 ! r_clk $end
$var wire 1 " r_req $end
$var wire 1 # r_rst $end
$var wire 5 8 w_g_syn_addr [4:0] $end
$var wire 5 9 r_g_addr [4:0] $end
$var wire 1 / r_empty $end
$var reg 5 : r_addr [4:0] $end
$scope module write_comtrol $end
$var wire 5 ; bin [4:0] $end
$var wire 1 < high_bit_bin $end
$var wire 5 = gray [4:0] $end
$var reg 4 > low_bit_gray [3:0] $end
$var integer 32 ? i [31:0] $end
$upscope $end
$upscope $end
$scope module asyn_fifo_syn_r $end
$var wire 1 $ rst_n $end
$var wire 1 ! syn_clk $end
$var wire 5 @ syn_data_out [4:0] $end
$var wire 5 A syn_data_in [4:0] $end
$var reg 5 B reg_0 [4:0] $end
$var reg 5 C reg_1 [4:0] $end
$upscope $end
$scope module asyn_fifo_syn_w $end
$var wire 1 $ rst_n $end
$var wire 1 % syn_clk $end
$var wire 5 D syn_data_in [4:0] $end
$var wire 5 E syn_data_out [4:0] $end
$var reg 5 F reg_0 [4:0] $end
$var reg 5 G reg_1 [4:0] $end
$upscope $end
$scope module asyn_fifo_write_control $end
$var wire 5 H r_g_syn_addr [4:0] $end
$var wire 1 % w_clk $end
$var wire 1 ' w_req $end
$var wire 1 ( w_rst $end
$var wire 5 I w_g_addr [4:0] $end
$var wire 1 + w_full $end
$var reg 5 J w_addr [4:0] $end
$scope module write_control $end
$var wire 5 K bin [4:0] $end
$var wire 1 L high_bit_bin $end
$var wire 5 M gray [4:0] $end
$var reg 4 N low_bit_gray [3:0] $end
$var integer 32 O i [31:0] $end
$upscope $end
$upscope $end
$upscope $end
$upscope $end
$enddefinitions $end
#0
$dumpvars
bx O
bx N
bx M
xL
bx K
bx J
bx I
bx H
bx G
bx F
bx E
bx D
bx C
bx B
bx A
bx @
bx ?
bx >
bx =
x<
bx ;
bx :
bx 9
bx 8
bx 7
b0 6
bx 5
bx 4
03
02
bx 1
bx 0
x/
bx .
bx -
bx ,
x+
bx *
bx )
1(
0'
b0 &
0%
1$
1#
0"
0!
$end
#20
0+
1/
b0 >
b100 ?
b0 .
b0 9
b0 =
b0 D
0<
b0 4
b0 N
b100 O
b0 *
b0 A
b0 I
b0 M
0L
b0 5
b0 )
b0 8
b0 @
b0 C
b0 B
b0 -
b0 E
b0 G
b0 H
b0 F
b0 1
b0 :
b0 ;
b0 ,
b0 J
b0 K
0$
0#
0(
#40
1!
#50
1%
#70
1$
1#
1(
#80
0!
#100
0%
#120
1!
#150
1%
#160
0!
#200
1!
0%
#220
12
1'
#240
0!
#250
b1 *
b1 A
b1 I
b1 M
b1 N
b100 O
b1 5
b1 ,
b1 J
b1 K
1%
#280
b1 B
1!
#300
0%
#320
0!
b1 &
b1 6
#350
b11 *
b11 A
b11 I
b11 M
b11 N
b100 O
b10 5
b10 ,
b10 J
b10 K
1%
#360
0/
b1 )
b1 8
b1 @
b1 C
b11 B
1!
#400
0!
0%
#420
b10 &
b10 6
#440
b11 )
b11 8
b11 @
b11 C
1!
#450
b10 *
b10 A
b10 I
b10 M
b10 N
b100 O
b11 5
b11 ,
b11 J
b11 K
1%
#480
0!
#500
0%
#520
b10 B
1!
b11 &
b11 6
#550
b110 *
b110 A
b110 I
b110 M
b110 N
b100 O
b100 5
b100 ,
b100 J
b100 K
1%
#560
0!
#600
b10 )
b10 8
b10 @
b10 C
b110 B
1!
0%
#620
b100 &
b100 6
#640
0!
#650
b111 *
b111 A
b111 I
b111 M
b111 N
b100 O
b101 5
b101 ,
b101 J
b101 K
1%
#680
b110 )
b110 8
b110 @
b110 C
b111 B
1!
#700
0%
#720
0!
b101 &
b101 6
#750
b101 *
b101 A
b101 I
b101 M
b101 N
b100 O
b110 5
b110 ,
b110 J
b110 K
1%
#760
b111 )
b111 8
b111 @
b111 C
b101 B
1!
#800
0!
0%
#820
b110 &
b110 6
#840
b101 )
b101 8
b101 @
b101 C
1!
#850
b100 *
b100 A
b100 I
b100 M
b100 N
b100 O
b111 5
b111 ,
b111 J
b111 K
1%
#880
0!
#900
0%
#920
b100 B
1!
b111 &
b111 6
#950
b1100 *
b1100 A
b1100 I
b1100 M
b1100 N
b100 O
b1000 5
b1000 ,
b1000 J
b1000 K
1%
#960
0!
#1000
b100 )
b100 8
b100 @
b100 C
b1100 B
1!
0%
#1020
b1000 &
b1000 6
#1040
0!
#1050
b1101 *
b1101 A
b1101 I
b1101 M
b1101 N
b100 O
b1001 5
b1001 ,
b1001 J
b1001 K
1%
#1080
b1100 )
b1100 8
b1100 @
b1100 C
b1101 B
1!
#1100
0%
#1120
0!
b1001 &
b1001 6
#1150
b1111 *
b1111 A
b1111 I
b1111 M
b1111 N
b100 O
b1010 5
b1010 ,
b1010 J
b1010 K
1%
#1160
b1101 )
b1101 8
b1101 @
b1101 C
b1111 B
1!
#1200
0!
0%
#1220
b1010 &
b1010 6
#1240
b1111 )
b1111 8
b1111 @
b1111 C
1!
#1250
b1110 *
b1110 A
b1110 I
b1110 M
b1110 N
b100 O
b1011 5
b1011 ,
b1011 J
b1011 K
1%
#1280
0!
#1300
0%
#1320
b1110 B
1!
b1011 &
b1011 6
#1350
b1010 *
b1010 A
b1010 I
b1010 M
b1010 N
b100 O
b1100 5
b1100 ,
b1100 J
b1100 K
1%
#1360
0!
#1400
b1110 )
b1110 8
b1110 @
b1110 C
b1010 B
1!
0%
#1420
b1100 &
b1100 6
#1440
0!
#1450
b1011 *
b1011 A
b1011 I
b1011 M
b1011 N
b100 O
b1101 5
b1101 ,
b1101 J
b1101 K
1%
#1480
b1010 )
b1010 8
b1010 @
b1010 C
b1011 B
1!
#1500
0%
#1520
0!
b1101 &
b1101 6
#1550
b1001 *
b1001 A
b1001 I
b1001 M
b1001 N
b100 O
b1110 5
b1110 ,
b1110 J
b1110 K
1%
#1560
b1011 )
b1011 8
b1011 @
b1011 C
b1001 B
1!
#1600
0!
0%
#1620
b1110 &
b1110 6
#1640
b1001 )
b1001 8
b1001 @
b1001 C
1!
#1650
b1000 *
b1000 A
b1000 I
b1000 M
b1000 N
b100 O
b1111 5
b1111 ,
b1111 J
b1111 K
1%
#1680
0!
#1700
0%
#1720
b1000 B
1!
b1111 &
b1111 6
#1750
02
1+
b100 O
b11000 *
b11000 A
b11000 I
b11000 M
1L
b0 5
b10000 ,
b10000 J
b10000 K
1%
#1760
0!
#1800
b1000 )
b1000 8
b1000 @
b1000 C
b11000 B
1!
0%
#1820
b10000 &
b10000 6
#1840
0!
#1850
1%
#1880
b11000 )
b11000 8
b11000 @
b11000 C
1!
#1900
0%
#1920
0!
b10001 &
b10001 6
#1950
1%
#1960
1!
#2000
13
0!
0%
1"
0'
#2040
b1 .
b1 9
b1 =
b1 D
b1 >
b100 ?
b1 4
b0 0
b0 7
b1 1
b1 :
b1 ;
1!
#2050
b1 F
1%
#2080
0!
#2100
0%
#2120
b11 .
b11 9
b11 =
b11 D
b11 >
b100 ?
b10 4
b1 0
b1 7
b10 1
b10 :
b10 ;
1!
#2150
0+
b1 -
b1 E
b1 G
b1 H
b11 F
1%
#2160
0!
#2200
b10 .
b10 9
b10 =
b10 D
b10 >
b100 ?
b11 4
b10 0
b10 7
b11 1
b11 :
b11 ;
1!
0%
#2240
0!
#2250
b11 -
b11 E
b11 G
b11 H
b10 F
1%
#2280
b110 .
b110 9
b110 =
b110 D
b110 >
b100 ?
b100 4
b11 0
b11 7
b100 1
b100 :
b100 ;
1!
#2300
0%
#2320
0!
#2350
b10 -
b10 E
b10 G
b10 H
b110 F
1%
#2360
b111 .
b111 9
b111 =
b111 D
b111 >
b100 ?
b101 4
b100 0
b100 7
b101 1
b101 :
b101 ;
1!
#2400
0!
0%
#2440
b101 .
b101 9
b101 =
b101 D
b101 >
b100 ?
b110 4
b101 0
b101 7
b110 1
b110 :
b110 ;
1!
#2450
b110 -
b110 E
b110 G
b110 H
b101 F
1%
#2480
0!
#2500
0%
#2520
b100 .
b100 9
b100 =
b100 D
b100 >
b100 ?
b111 4
b110 0
b110 7
b111 1
b111 :
b111 ;
1!
#2550
b101 -
b101 E
b101 G
b101 H
b100 F
1%
#2560
0!
#2600
b1100 .
b1100 9
b1100 =
b1100 D
b1100 >
b100 ?
b1000 4
b111 0
b111 7
b1000 1
b1000 :
b1000 ;
1!
0%
#2640
0!
#2650
b100 -
b100 E
b100 G
b100 H
b1100 F
1%
#2680
b1101 .
b1101 9
b1101 =
b1101 D
b1101 >
b100 ?
b1001 4
b1000 0
b1000 7
b1001 1
b1001 :
b1001 ;
1!
#2700
0%
#2720
0!
#2750
b1100 -
b1100 E
b1100 G
b1100 H
b1101 F
1%
#2760
b1111 .
b1111 9
b1111 =
b1111 D
b1111 >
b100 ?
b1010 4
b1001 0
b1001 7
b1010 1
b1010 :
b1010 ;
1!
#2800
0!
0%
#2840
b1110 .
b1110 9
b1110 =
b1110 D
b1110 >
b100 ?
b1011 4
b1010 0
b1010 7
b1011 1
b1011 :
b1011 ;
1!
#2850
b1101 -
b1101 E
b1101 G
b1101 H
b1110 F
1%
#2880
0!
#2900
0%
#2920
b1010 .
b1010 9
b1010 =
b1010 D
b1010 >
b100 ?
b1100 4
b1011 0
b1011 7
b1100 1
b1100 :
b1100 ;
1!
#2950
b1110 -
b1110 E
b1110 G
b1110 H
b1010 F
1%
#2960
0!
#3000
b1011 .
b1011 9
b1011 =
b1011 D
b1011 >
b100 ?
b1101 4
b1100 0
b1100 7
b1101 1
b1101 :
b1101 ;
1!
0%
#3040
0!
#3050
b1010 -
b1010 E
b1010 G
b1010 H
b1011 F
1%
#3080
b1001 .
b1001 9
b1001 =
b1001 D
b1001 >
b100 ?
b1110 4
b1101 0
b1101 7
b1110 1
b1110 :
b1110 ;
1!
#3100
0%
#3120
0!
#3150
b1011 -
b1011 E
b1011 G
b1011 H
b1001 F
1%
#3160
b1000 .
b1000 9
b1000 =
b1000 D
b1000 >
b100 ?
b1111 4
b1110 0
b1110 7
b1111 1
b1111 :
b1111 ;
1!
#3200
0!
0%
#3240
03
1/
b100 ?
b11000 .
b11000 9
b11000 =
b11000 D
1<
b0 4
b1111 0
b1111 7
b10000 1
b10000 :
b10000 ;
1!
#3250
b1001 -
b1001 E
b1001 G
b1001 H
b11000 F
1%
#3280
0!
#3300
0%
#3320
1!
#3350
b11000 -
b11000 E
b11000 G
b11000 H
1%
#3360
0!
#3400
1!
0%
#3410
b0 &
b0 6
0"
